amplpy/__init__.pyi
amplpy/__init__.py
amplpy/utils.py
amplpy/ampl.cpython-39-darwin.so
amplpy/tools/__init__.py
amplpy/tests/test_outputhandler.py
amplpy/tests/test_iterators.py
amplpy/tests/test_ampl.py
amplpy/tests/TestBase.py
amplpy/tests/test_exceptions.py
amplpy/tests/__init__.py
amplpy/tests/data.csv
amplpy/tests/test_entities.py
amplpy/tests/context.py
amplpy/tests/test_properties.py
amplpy/tests/__main__.py
amplpy/tests/test_environment.py
amplpy/tests/test_dataframe.py
amplpy/bundle/__main__.py
amplpy/tests_camel/test_iterators.py
amplpy/tests_camel/test_ampl.py
amplpy/tests_camel/TestBase.py
amplpy/tests_camel/__init__.py
amplpy/tests_camel/data.csv
amplpy/tests_camel/test_entities.py
amplpy/tests_camel/context.py
amplpy/tests_camel/test_properties.py
amplpy/tests_camel/__main__.py
amplpy/tests_camel/test_environment.py
amplpy/tests_camel/test_dataframe.py
amplpy/amplpython/__init__.py
amplpy/amplpython/cppinterface/include/.gitignore
amplpy/amplpython/cppinterface/include/ampl/errorhandler.h
amplpy/amplpython/cppinterface/include/ampl/declarations.h
amplpy/amplpython/cppinterface/include/ampl/arg.h
amplpy/amplpython/cppinterface/include/ampl/ampl.h
amplpy/amplpython/cppinterface/include/ampl/slice.h
amplpy/amplpython/cppinterface/include/ampl/variant_c.h
amplpy/amplpython/cppinterface/include/ampl/optional.h
amplpy/amplpython/cppinterface/include/ampl/output.h
amplpy/amplpython/cppinterface/include/ampl/tuple_c.h
amplpy/amplpython/cppinterface/include/ampl/environment.h
amplpy/amplpython/cppinterface/include/ampl/cstringref.h
amplpy/amplpython/cppinterface/include/ampl/runnable.h
amplpy/amplpython/cppinterface/include/ampl/.gitignore
amplpy/amplpython/cppinterface/include/ampl/macros.h
amplpy/amplpython/cppinterface/include/ampl/output_c.h
amplpy/amplpython/cppinterface/include/ampl/dataframe_c.h
amplpy/amplpython/cppinterface/include/ampl/entity.h
amplpy-0.16.0.dist-info/RECORD
amplpy-0.16.0.dist-info/WHEEL
amplpy-0.16.0.dist-info/top_level.txt
amplpy-0.16.0.dist-info/METADATA
amplpy-0.16.0.dist-info/licenses/LICENSE
